{
    "1": {
        "name": "Default Location",
        "cost": 0
    },
    "2": {
        "name": "Beach",
        "cost": 2800
    },
    "3": {
        "name": "Forest",
        "cost": 2700
    },
    "4": {
        "name": "Mountain",
        "cost": 2800 
    },
    "5": {
        "name": "Age Of Dinosaurs",
        "cost": 0
    },
    "6": {
        "name": "Distant Planet",
        "cost": 1800
    },
    "7": {
        "name": "Soccer Pitch",
        "cost": 1800
    },
    "8": {
        "name": "Undersea",
        "cost": 1800
    },
    "9": {
        "name": "Icy Wonderland",
        "cost": 0
    },
    "11": {
        "name": "Default Location (Night)",
        "cost": 0
    },
    "12": {
        "name": "Beach (Night)",
        "cost": 2800
    },
    "13": {
        "name": "Forest (Night)",
        "cost": 2700
    },
    "14": {
        "name": "Mountain (Night)",
        "cost": 2800
    },
    "15": {
        "name": "Glacial Box Realm",
        "cost": 2800
    },
    "16": {
        "name": "Top O' the Morning",
        "cost": 2800
    },
    "17": {
        "name": "Top O' the Evening",
        "cost": 2800
    },
    "18": {
      "name": "Default Location (Sunset)",
      "cost": 0
    },
    "19": {
      "name": "Beach (Sunset)",
      "cost": 2800
    },
    "20": {
      "name": "Forest (Sunset)",
      "cost": 2800
    },
    "21": {
      "name": "Mountain (Sunset)",
      "cost": 2800
    },
    "22": {
      "name": "Corn Maze",
      "cost": 0
    }
}